README.txt
setup.py
collective/__init__.py
collective.recipe.hudsonjob.egg-info/PKG-INFO
collective.recipe.hudsonjob.egg-info/SOURCES.txt
collective.recipe.hudsonjob.egg-info/dependency_links.txt
collective.recipe.hudsonjob.egg-info/entry_points.txt
collective.recipe.hudsonjob.egg-info/namespace_packages.txt
collective.recipe.hudsonjob.egg-info/not-zip-safe
collective.recipe.hudsonjob.egg-info/requires.txt
collective.recipe.hudsonjob.egg-info/top_level.txt
collective/recipe/__init__.py
collective/recipe/hudsonjob/__init__.py
collective/recipe/hudsonjob/tests/__init__.py
collective/recipe/hudsonjob/tests/test_recipe.py