Metadata-Version: 1.0
Name: collective.recipe.hudsonjob
Version: 0.1
Summary: Hudson configuration for Plone in buildout
Home-page: UNKNOWN
Author: UNKNOWN
Author-email: UNKNOWN
License: ZPL
Keywords: hudson,plone
Platform: UNKNOWN
Classifier: Framework :: Buildout
Classifier: Intended Audience :: Developers
Classifier: Topic :: Software Development :: Build Tools
Classifier: License :: OSI Approved :: Zope Public License
